MANIFEST.in
setup.py
nebm_plot_tools/__init__.py
nebm_plot_tools/annotate_snapshots.py
nebm_plot_tools/nebm_plot_tools.py
nebm_plot_tools/npt_colormaps.py
nebm_plot_tools.egg-info/PKG-INFO
nebm_plot_tools.egg-info/SOURCES.txt
nebm_plot_tools.egg-info/dependency_links.txt
nebm_plot_tools.egg-info/requires.txt
nebm_plot_tools.egg-info/top_level.txt
nebm_plot_tools/cmaps/parula.txt