Metadata-Version: 1.0
Name: nebm-plot-tools
Version: 1.1
Summary: Plotting library for NEBM data based on Matplotlib and Mayavi
Home-page: https://github.com/davidcortesortuno/nebm_plot_tools
Author: D. I. Cortes
Author-email: UNKNOWN
License: MIT
Platform: UNKNOWN
